zstd_asgi/__init__.py
zstd_asgi-1.0.dist-info/licenses/LICENSE.md
zstd_asgi-1.0.dist-info/METADATA
zstd_asgi-1.0.dist-info/WHEEL
zstd_asgi-1.0.dist-info/top_level.txt
zstd_asgi-1.0.dist-info/RECORD
